export.py
export-0.1.2.dist-info/pydist.json
export-0.1.2.dist-info/METADATA
export-0.1.2.dist-info/RECORD
export-0.1.2.dist-info/WHEEL
export-0.1.2.dist-info/DESCRIPTION.rst
export-0.1.2.dist-info/top_level.txt
