Metadata-Version: 1.1
Name: export
Version: 0.1.2
Summary: A Python package joke.
Home-page: http://github.com/zsiciarz/export
Author: Zbigniew Siciarz
Author-email: zbigniew@siciarz.net
License: MIT
Download-URL: http://pypi.python.org/pypi/export
Platform: any
Classifier: Development Status :: 5 - Production/Stable
Classifier: Intended Audience :: Developers
Classifier: License :: OSI Approved :: MIT License
Classifier: Operating System :: OS Independent
Classifier: Programming Language :: Python
Classifier: Programming Language :: Python :: 2
Classifier: Programming Language :: Python :: 3
Classifier: Topic :: Utilities
